jj_district42/__init__.py
jj_district42/_version.py
jj_district42/py.typed
jj_district42/history_request/__init__.py
jj_district42/history_request/_history_request_generator.py
jj_district42/history_request/_history_request_schema.py
jj_district42/history_request/_history_request_substitutor.py
jj_district42/history_request/_history_request_validator.py
jj_district42/history_response/__init__.py
jj_district42/history_response/_history_response_generator.py
jj_district42/history_response/_history_response_schema.py
jj_district42/history_response/_history_response_substitutor.py
jj_district42/history_response/_history_response_validator.py
jj_district42/types/__init__.py
jj_district42/types/header_list/__init__.py
jj_district42/types/istr/__init__.py
jj_district42/types/param_list/__init__.py
jj_district42/utils/__init__.py
tests/history_request/__init__.py
tests/history_request/_utils.py
tests/history_request/test_history_request_generator.py
tests/history_request/test_history_request_representor.py
tests/history_request/test_history_request_schema.py
tests/history_request/test_history_request_substitutor.py
tests/history_request/test_history_request_validator.py
tests/history_request/test_history_request_validator_headers.py
tests/history_request/test_history_request_validator_params.py
tests/history_response/__init__.py
tests/history_response/_utils.py
tests/history_response/test_history_response_generator.py
tests/history_response/test_history_response_representor.py
tests/history_response/test_history_response_schema.py
tests/history_response/test_history_response_substitutor.py
tests/history_response/test_history_response_validator.py
tests/history_response/test_history_response_validator_headers.py
tests/types/__init__.py
tests/types/header_list/__init__.py
tests/types/header_list/test_header_list_generator.py
tests/types/header_list/test_header_list_representor.py
tests/types/header_list/test_header_list_schema.py
jj_district42-1.2.2.dist-info/LICENSE
jj_district42-1.2.2.dist-info/METADATA
jj_district42-1.2.2.dist-info/WHEEL
jj_district42-1.2.2.dist-info/top_level.txt
jj_district42-1.2.2.dist-info/RECORD
