Metadata-Version: 2.1
Name: jj-district42
Version: 1.2.2
Home-page: https://github.com/jj-mock/jj-district42
Author: Nikita Tsvetkov
Author-email: tsv1@fastmail.com
License: Apache-2.0
Project-URL: Docs, https://jj-mock.io/docs/integrations/d42
Project-URL: GitHub, https://github.com/jj-mock/jj-district42
Classifier: License :: OSI Approved :: Apache Software License
Classifier: Programming Language :: Python :: 3.8
Classifier: Programming Language :: Python :: 3.9
Classifier: Programming Language :: Python :: 3.10
Classifier: Programming Language :: Python :: 3.11
Classifier: Programming Language :: Python :: 3.12
Classifier: Typing :: Typed
Requires-Python: >=3.8
License-File: LICENSE
Requires-Dist: d42<2.0,>=1.5
Requires-Dist: district42-exp-types<1.0,>=0.9
Requires-Dist: jj<3.0,>=2.3.1
Requires-Dist: niltype<1.0,>=0.3
Requires-Dist: th<1.0,>=0.3
